
{"header":["Accept: application/json"],"response_header":["Content-Type: application/json"],"description":"**List actions for gel resource.**\n\n* `create` creates a new gel plate via HTTP POST request\n* `read` returns the list of actions for a gel plate resource via HTTP GET request\n* `first` lists the first gel plates resources in a page browsing system\n* `last` lists the last gel plates resources in a page browsing system\n","method":"GET","url":"/gels","status":200,"response":"{ \"gels\": {\n    \"actions\": {\n        \"create\": \"/gels\",\n        \"read\": \"/gels\",\n        \"first\": \"/gels/page=1\",\n        \"last\": \"/gels/page=-1\"\n    }\n} }\n"}
